pkoffice/__init__.py
pkoffice/excel.py
pkoffice/file.py
pkoffice/outlook.py
pkoffice/selenium.py
pkoffice/sql.py
pkoffice-0.0.49.dist-info/METADATA
pkoffice-0.0.49.dist-info/WHEEL
pkoffice-0.0.49.dist-info/top_level.txt
pkoffice-0.0.49.dist-info/RECORD
